sprich/__init__.py
sprich/grammar.lark
sprich/sprich.py
sprich-0.1.dist-info/LICENSE
sprich-0.1.dist-info/METADATA
sprich-0.1.dist-info/WHEEL
sprich-0.1.dist-info/entry_points.txt
sprich-0.1.dist-info/top_level.txt
sprich-0.1.dist-info/RECORD
