Metadata-Version: 2.1
Name: sprich
Version: 0.1
Summary: A compiler for interactive dialogs.
Home-page: https://github.com/haselkern/sprich
Author: Lars Martens
Author-email: contact@haselkern.com
License: UNKNOWN
Platform: UNKNOWN
Classifier: Programming Language :: Python :: 3
Classifier: Programming Language :: Python :: 3.7
Classifier: License :: OSI Approved :: MIT License
Classifier: Operating System :: OS Independent
Classifier: Development Status :: 4 - Beta
Requires-Dist: lark-parser (==0.7.1)
